{
  "songID": "entry_100013",
  "title": "Sonatina En Si Sostenido",
  "artist": "Chano",
  "spotifyID": "1iTqFAz1RlBBCPLK1osdc9",
  "key": null,
  "tempo": null,
  "timeSignature": "4/4",
  "sections": [
    {
      "type": "Verse",
      "chords": [
        "C",
        "B7",
        "Emin",
        "Amin",
        "Dmin",
        "F",
        "G",
        "C",
        "B7",
        "Emin",
        "C7",
        "F",
        "G",
        "C",
        "F",
        "G",
        "C",
        "F",
        "G",
        "Amin",
        "F",
        "E7",
        "Amin",
        "Amin/G",
        "F",
        "G"
      ],
      "rawChords": [
        "C",
        "B7",
        "Emin",
        "Amin",
        "Dmin",
        "F",
        "G",
        "C",
        "B7",
        "Emin",
        "C7",
        "F",
        "G",
        "C",
        "F",
        "G",
        "C",
        "F",
        "G",
        "Amin",
        "F",
        "E7",
        "Amin",
        "Amin/G",
        "F",
        "G"
      ],
      "length": 26,
      "cadence": "none",
      "tags": [
        "key:F",
        "mode:major",
        "key_confidence:0.25",
        "progression:v-?-#iv-?-?-?-?-i-?-ii-?-v-?-#iv-?-?-v-?-i-?-ii-?-v-?-i-?-ii-?-v-?-i-?-ii-?-?-i-?-vii-?-?-?-i-?-ii-?",
        "closure:false"
      ],
      "notes": "",
      "key": "F",
      "mode": "major"
    },
    {
      "type": "Chorus",
      "chords": [
        "F",
        "G",
        "C",
        "F",
        "G",
        "Amin",
        "F",
        "E7",
        "Amin",
        "F",
        "G",
        "C"
      ],
      "rawChords": [
        "F",
        "G",
        "C",
        "F",
        "G",
        "Amin",
        "F",
        "E7",
        "Amin",
        "F",
        "G",
        "C"
      ],
      "length": 12,
      "cadence": "none",
      "tags": [
        "key:C",
        "mode:major",
        "key_confidence:0.29",
        "progression:iv-?-v-?-i-?-iv-?-v-?-?-iv-?-iii-?-?-iv-?-v-?-i-?",
        "closure:false"
      ],
      "notes": "",
      "key": "C",
      "mode": "major"
    },
    {
      "type": "Verse",
      "chords": [
        "B7",
        "Emin",
        "Amin",
        "Dmin",
        "F",
        "G",
        "C",
        "B7",
        "Emin",
        "C7",
        "F",
        "G",
        "C",
        "F",
        "G",
        "C",
        "F",
        "G",
        "Amin",
        "F",
        "E7",
        "Amin",
        "Amin/G",
        "F",
        "G"
      ],
      "rawChords": [
        "B7",
        "Emin",
        "Amin",
        "Dmin",
        "F",
        "G",
        "C",
        "B7",
        "Emin",
        "C7",
        "F",
        "G",
        "C",
        "F",
        "G",
        "C",
        "F",
        "G",
        "Amin",
        "F",
        "E7",
        "Amin",
        "Amin/G",
        "F",
        "G"
      ],
      "length": 25,
      "cadence": "none",
      "tags": [
        "key:C",
        "mode:major",
        "key_confidence:0.23",
        "progression:vii-?-?-?-?-iv-?-v-?-i-?-vii-?-?-i-?-iv-?-v-?-i-?-iv-?-v-?-i-?-iv-?-v-?-?-iv-?-iii-?-?-?-iv-?-v-?",
        "closure:false"
      ],
      "notes": "",
      "key": "C",
      "mode": "major"
    },
    {
      "type": "Chorus",
      "chords": [
        "F",
        "G",
        "C",
        "F",
        "G",
        "Amin",
        "F",
        "E7",
        "Amin",
        "F",
        "G",
        "C",
        "F",
        "G",
        "C",
        "F",
        "G",
        "Amin",
        "F",
        "E7",
        "Amin",
        "F",
        "G",
        "C",
        "F",
        "G",
        "C",
        "F",
        "G",
        "Amin",
        "F",
        "E7",
        "Amin",
        "F",
        "G",
        "C"
      ],
      "rawChords": [
        "F",
        "G",
        "C",
        "F",
        "G",
        "Amin",
        "F",
        "E7",
        "Amin",
        "F",
        "G",
        "C",
        "F",
        "G",
        "C",
        "F",
        "G",
        "Amin",
        "F",
        "E7",
        "Amin",
        "F",
        "G",
        "C",
        "F",
        "G",
        "C",
        "F",
        "G",
        "Amin",
        "F",
        "E7",
        "Amin",
        "F",
        "G",
        "C"
      ],
      "length": 36,
      "cadence": "none",
      "tags": [
        "key:C",
        "mode:major",
        "key_confidence:0.29",
        "progression:iv-?-v-?-i-?-iv-?-v-?-?-iv-?-iii-?-?-iv-?-v-?-i-?-iv-?-v-?-i-?-iv-?-v-?-?-iv-?-iii-?-?-iv-?-v-?-i-?-iv-?-v-?-i-?-iv-?-v-?-?-iv-?-iii-?-?-iv-?-v-?-i-?",
        "closure:false"
      ],
      "notes": "",
      "key": "C",
      "mode": "major"
    }
  ],
  "structure": [
    "Verse",
    "Chorus",
    "Verse",
    "Chorus"
  ],
  "tags": [],
  "album": "El Doble",
  "release_date": "2019-09-27",
  "duration_ms": 178106
}