{
  "songID": "entry_0656",
  "title": "Wake Up",
  "artist": "Mr. Big",
  "spotifyID": "4QO00F2MwWmZ37IeoSWejw",
  "key": null,
  "tempo": null,
  "timeSignature": "4/4",
  "sections": [
    {
      "type": "Intro",
      "chords": [
        "Asus2",
        "E",
        "B"
      ],
      "rawChords": [
        "Asus2",
        "E",
        "B"
      ],
      "length": 3,
      "cadence": "none",
      "tags": [
        "key:E",
        "mode:major",
        "key_confidence:0.21",
        "progression:?-i-?-v-?",
        "closure:false"
      ],
      "notes": "",
      "key": "E",
      "mode": "major"
    },
    {
      "type": "Verse",
      "chords": [
        "A",
        "E",
        "B",
        "A",
        "E",
        "B",
        "A",
        "E/Gs",
        "Bsus4",
        "A",
        "E/Gs",
        "Bsus4"
      ],
      "rawChords": [
        "A",
        "E",
        "B",
        "A",
        "E",
        "B",
        "A",
        "E/Gs",
        "Bsus4",
        "A",
        "E/Gs",
        "Bsus4"
      ],
      "length": 12,
      "cadence": "none",
      "tags": [
        "key:A",
        "mode:minor",
        "key_confidence:0.33",
        "progression:i-?-v-?-ii-?-i-?-v-?-ii-?-i-?-?-?-i-?-?-?",
        "closure:false"
      ],
      "notes": "",
      "key": "A",
      "mode": "minor"
    },
    {
      "type": "Chorus",
      "chords": [
        "E",
        "Bsus4",
        "Fsmin7",
        "A",
        "E",
        "Bsus4",
        "Fsmin7",
        "A",
        "Csmin7",
        "A",
        "Fsmin7",
        "A",
        "E",
        "Bsus4",
        "Dadd13"
      ],
      "rawChords": [
        "E",
        "Bsus4",
        "Fsmin7",
        "A",
        "E",
        "Bsus4",
        "Fsmin7",
        "A",
        "Csmin7",
        "A",
        "Fsmin7",
        "A",
        "E",
        "Bsus4",
        "Dadd13"
      ],
      "length": 15,
      "cadence": "none",
      "tags": [
        "key:A",
        "mode:minor",
        "key_confidence:0.26",
        "progression:v-?-?-?-i-?-v-?-?-?-i-?-?-i-?-?-i-?-v-?-?-?",
        "closure:false"
      ],
      "notes": "",
      "key": "A",
      "mode": "minor"
    },
    {
      "type": "Verse",
      "chords": [
        "A",
        "E",
        "B",
        "A",
        "E",
        "B",
        "A",
        "E/Gs",
        "Bsus4",
        "A",
        "E/Gs",
        "Bsus4"
      ],
      "rawChords": [
        "A",
        "E",
        "B",
        "A",
        "E",
        "B",
        "A",
        "E/Gs",
        "Bsus4",
        "A",
        "E/Gs",
        "Bsus4"
      ],
      "length": 12,
      "cadence": "none",
      "tags": [
        "key:A",
        "mode:minor",
        "key_confidence:0.33",
        "progression:i-?-v-?-ii-?-i-?-v-?-ii-?-i-?-?-?-i-?-?-?",
        "closure:false"
      ],
      "notes": "",
      "key": "A",
      "mode": "minor"
    },
    {
      "type": "Chorus",
      "chords": [
        "E",
        "Bsus4",
        "Fsmin7",
        "A",
        "E",
        "Bsus4",
        "Fsmin7",
        "A",
        "Csmin7",
        "A",
        "Fsmin7",
        "A",
        "E",
        "Bsus4",
        "Dadd13"
      ],
      "rawChords": [
        "E",
        "Bsus4",
        "Fsmin7",
        "A",
        "E",
        "Bsus4",
        "Fsmin7",
        "A",
        "Csmin7",
        "A",
        "Fsmin7",
        "A",
        "E",
        "Bsus4",
        "Dadd13"
      ],
      "length": 15,
      "cadence": "none",
      "tags": [
        "key:A",
        "mode:minor",
        "key_confidence:0.26",
        "progression:v-?-?-?-i-?-v-?-?-?-i-?-?-i-?-?-i-?-v-?-?-?",
        "closure:false"
      ],
      "notes": "",
      "key": "A",
      "mode": "minor"
    },
    {
      "type": "Bridge",
      "chords": [
        "Fsmin7",
        "G",
        "Bmin7",
        "Csus2",
        "Fsmin7",
        "G",
        "Bmin7",
        "A",
        "G"
      ],
      "rawChords": [
        "Fsmin7",
        "G",
        "Bmin7",
        "Csus2",
        "Fsmin7",
        "G",
        "Bmin7",
        "A",
        "G"
      ],
      "length": 9,
      "cadence": "none",
      "tags": [
        "key:C",
        "mode:major",
        "key_confidence:0.00",
        "progression:?-v-?-?-?-?-v-?-?-vi-?-v-?",
        "closure:false"
      ],
      "notes": "",
      "key": "C",
      "mode": "major"
    },
    {
      "type": "Solo",
      "chords": [
        "Csmin7",
        "D",
        "E",
        "Csmin7",
        "A",
        "Fsmin7",
        "A",
        "E",
        "Bsus4",
        "Dadd13"
      ],
      "rawChords": [
        "Csmin7",
        "D",
        "E",
        "Csmin7",
        "A",
        "Fsmin7",
        "A",
        "E",
        "Bsus4",
        "Dadd13"
      ],
      "length": 10,
      "cadence": "none",
      "tags": [
        "key:A",
        "mode:minor",
        "key_confidence:0.42",
        "progression:?-iv-?-v-?-?-i-?-?-i-?-v-?-?-?",
        "closure:false"
      ],
      "notes": "",
      "key": "A",
      "mode": "minor"
    },
    {
      "type": "Chorus",
      "chords": [
        "E",
        "Bsus4",
        "Fsmin7",
        "A",
        "E",
        "Bsus4",
        "Fsmin7",
        "A",
        "E",
        "Bsus4",
        "Fsmin7",
        "A",
        "E",
        "Bsus4",
        "Fsmin7",
        "A",
        "Csmin7",
        "A",
        "Fsmin7",
        "A",
        "E",
        "Bsus4",
        "Dadd13",
        "E"
      ],
      "rawChords": [
        "E",
        "Bsus4",
        "Fsmin7",
        "A",
        "E",
        "Bsus4",
        "Fsmin7",
        "A",
        "E",
        "Bsus4",
        "Fsmin7",
        "A",
        "E",
        "Bsus4",
        "Fsmin7",
        "A",
        "Csmin7",
        "A",
        "Fsmin7",
        "A",
        "E",
        "Bsus4",
        "Dadd13",
        "E"
      ],
      "length": 24,
      "cadence": "none",
      "tags": [
        "key:A",
        "mode:major",
        "key_confidence:0.29",
        "progression:v-?-?-?-i-?-v-?-?-?-i-?-v-?-?-?-i-?-v-?-?-?-i-?-?-i-?-?-i-?-v-?-?-?-v-?",
        "closure:false"
      ],
      "notes": "",
      "key": "A",
      "mode": "major"
    }
  ],
  "structure": [
    "Intro",
    "Verse",
    "Chorus",
    "Verse",
    "Chorus",
    "Bridge",
    "Solo",
    "Chorus"
  ],
  "tags": [],
  "album": "Actual Size",
  "release_date": "2001-09-25",
  "duration_ms": 224866
}