{
  "songID": "entry_101754",
  "title": "To You",
  "artist": "OR3O",
  "spotifyID": "683g6C3gRUCPCe7Ut6QVpE",
  "key": null,
  "tempo": null,
  "timeSignature": "4/4",
  "sections": [
    {
      "type": "Intro",
      "chords": [
        "G",
        "Amin7",
        "Bmin7",
        "Bbmin7",
        "Amin",
        "C7",
        "Bmin7",
        "G",
        "E7",
        "Amin7",
        "Bmin7"
      ],
      "rawChords": [
        "G",
        "Amin7",
        "Bmin7",
        "Bbmin7",
        "Amin",
        "C7",
        "Bmin7",
        "G",
        "E7",
        "Amin7",
        "Bmin7"
      ],
      "length": 11,
      "cadence": "none",
      "tags": [
        "key:C",
        "mode:major",
        "key_confidence:0.46",
        "progression:v-?-?-?-?-?-i-?-?-v-?-iii-?-?-?",
        "closure:false"
      ],
      "notes": "",
      "key": "C",
      "mode": "major"
    },
    {
      "type": "Verse",
      "chords": [
        "G",
        "Amin7",
        "Bmin7",
        "Amin7",
        "G",
        "E7",
        "Amin7",
        "Bmin7",
        "G",
        "Amin7",
        "Bmin7",
        "Amin7",
        "G",
        "Amin7",
        "Bmin7",
        "Amin7"
      ],
      "rawChords": [
        "G",
        "Amin7",
        "Bmin7",
        "Amin7",
        "G",
        "E7",
        "Amin7",
        "Bmin7",
        "G",
        "Amin7",
        "Bmin7",
        "Amin7",
        "G",
        "Amin7",
        "Bmin7",
        "Amin7"
      ],
      "length": 16,
      "cadence": "none",
      "tags": [
        "key:C",
        "mode:major",
        "key_confidence:0.21",
        "progression:v-?-?-?-?-v-?-iii-?-?-?-v-?-?-?-?-v-?-?-?-?",
        "closure:false"
      ],
      "notes": "",
      "key": "C",
      "mode": "major"
    },
    {
      "type": "Verse",
      "chords": [
        "G",
        "E7",
        "Amin7",
        "Bmin7",
        "G",
        "E7",
        "Amin7",
        "Bmin7",
        "G",
        "Amin7",
        "Bmin7",
        "Amin7",
        "G",
        "Amin7",
        "Bmin7",
        "Amin7",
        "E7",
        "G",
        "Amin",
        "D",
        "G",
        "Amin",
        "Bmin",
        "Dmin7",
        "B7",
        "G",
        "Amin",
        "D",
        "Bmin",
        "G",
        "Amin",
        "D",
        "Bmin",
        "Amin",
        "D7",
        "Dsus4"
      ],
      "rawChords": [
        "G",
        "E7",
        "Amin7",
        "Bmin7",
        "G",
        "E7",
        "Amin7",
        "Bmin7",
        "G",
        "Amin7",
        "Bmin7",
        "Amin7",
        "G",
        "Amin7",
        "Bmin7",
        "Amin7",
        "E7",
        "G",
        "Amin",
        "D",
        "G",
        "Amin",
        "Bmin",
        "Dmin7",
        "B7",
        "G",
        "Amin",
        "D",
        "Bmin",
        "G",
        "Amin",
        "D",
        "Bmin",
        "Amin",
        "D7",
        "Dsus4"
      ],
      "length": 36,
      "cadence": "none",
      "tags": [
        "key:C",
        "mode:major",
        "key_confidence:0.42",
        "progression:v-?-iii-?-?-?-v-?-iii-?-?-?-v-?-?-?-?-v-?-?-?-?-iii-?-v-?-?-ii-?-v-?-?-?-?-vii-?-v-?-?-ii-?-?-v-?-?-ii-?-?-?-ii-?-?",
        "closure:false"
      ],
      "notes": "",
      "key": "C",
      "mode": "major"
    },
    {
      "type": "Chorus",
      "chords": [
        "G",
        "Amin7",
        "Bmin7",
        "Dsus4",
        "E7",
        "Amin7",
        "G",
        "Bmin7",
        "G",
        "Amin7",
        "Bmin7",
        "Amin7",
        "G",
        "Amin7",
        "Bmin7",
        "D",
        "G"
      ],
      "rawChords": [
        "G",
        "Amin7",
        "Bmin7",
        "Dsus4",
        "E7",
        "Amin7",
        "G",
        "Bmin7",
        "G",
        "Amin7",
        "Bmin7",
        "Amin7",
        "G",
        "Amin7",
        "Bmin7",
        "D",
        "G"
      ],
      "length": 17,
      "cadence": "none",
      "tags": [
        "key:C",
        "mode:major",
        "key_confidence:0.31",
        "progression:v-?-?-?-?-iii-?-?-v-?-?-v-?-?-?-?-v-?-?-?-ii-?-v-?",
        "closure:false"
      ],
      "notes": "",
      "key": "C",
      "mode": "major"
    },
    {
      "type": "Chorus",
      "chords": [
        "Amin7",
        "Bmin7",
        "Dsus4",
        "E7",
        "Amin7",
        "G",
        "Bmin7",
        "G",
        "Amin7",
        "Bmin7",
        "Amin7",
        "G",
        "Amin7",
        "Bmin7",
        "D",
        "G"
      ],
      "rawChords": [
        "Amin7",
        "Bmin7",
        "Dsus4",
        "E7",
        "Amin7",
        "G",
        "Bmin7",
        "G",
        "Amin7",
        "Bmin7",
        "Amin7",
        "G",
        "Amin7",
        "Bmin7",
        "D",
        "G"
      ],
      "length": 16,
      "cadence": "none",
      "tags": [
        "key:C",
        "mode:major",
        "key_confidence:0.36",
        "progression:?-?-?-iii-?-?-v-?-?-v-?-?-?-?-v-?-?-?-ii-?-v-?",
        "closure:false"
      ],
      "notes": "",
      "key": "C",
      "mode": "major"
    },
    {
      "type": "Outro",
      "chords": [
        "Amin7",
        "Bmin7",
        "Dsus4",
        "G"
      ],
      "rawChords": [
        "Amin7",
        "Bmin7",
        "Dsus4",
        "G"
      ],
      "length": 4,
      "cadence": "none",
      "tags": [],
      "notes": ""
    }
  ],
  "structure": [
    "Intro",
    "Verse",
    "Verse",
    "Chorus",
    "Chorus",
    "Outro"
  ],
  "tags": [],
  "album": "Clover",
  "release_date": "2021-04-18",
  "duration_ms": 169263
}