{
  "title": "Rocket Ride",
  "artist": "Kiss",
  "bpm": 120,
  "source": "McGill Billboard + SALAMI",
  "sections": [
    {
      "id": "intro_1",
      "start_ms": 626,
      "duration_ms": 6756,
      "chords": [
        "F:5",
        "Gb:5",
        "G:5",
        "Ab:5",
        "A:5",
        "Bb:5",
        "B:5",
        "C:5"
      ],
      "sectionType": "Intro",
      "sectionLetter": "A",
      "sectionFunction": "Introduction",
      "sectionLabel": "A",
      "tags": [
        "salami_annotated",
        "timing_confidence:high"
      ]
    },
    {
      "id": "verse_1",
      "start_ms": 7383,
      "duration_ms": 13297,
      "chords": [
        "C:5",
        "Eb:min",
        "Eb:min",
        "Eb:min",
        "Eb:min",
        "Eb:min",
        "Eb:min",
        "Eb:min",
        "Eb:min",
        "Eb:min"
      ],
      "sectionType": "Verse",
      "sectionLetter": "B",
      "sectionFunction": "MainTheme",
      "sectionLabel": "B",
      "tags": [
        "salami_annotated",
        "timing_confidence:high"
      ]
    },
    {
      "id": "chorus_1",
      "start_ms": 20681,
      "duration_ms": 26501,
      "chords": [
        "Eb:min",
        "F:5",
        "Bb:5",
        "F:5",
        "Eb:5",
        "F:5",
        "Bb:5",
        "F:5",
        "Gb:5",
        "G:5",
        "Ab:5",
        "Ab:5",
        "Eb:min",
        "Eb:min",
        "Eb:min",
        "Eb:min",
        "Eb:min",
        "F:5",
        "Bb:5",
        "F:5",
        "Eb:5",
        "F:5",
        "Bb:5",
        "F:5",
        "Gb:5",
        "G:5",
        "Ab:5",
        "Ab:5",
        "Eb:min",
        "Eb:min",
        "Eb:min",
        "Eb:min"
      ],
      "sectionType": "Chorus",
      "sectionLetter": "C",
      "sectionFunction": "Hook",
      "sectionLabel": "C",
      "tags": [
        "salami_annotated",
        "timing_confidence:high"
      ]
    },
    {
      "id": "bridge_1",
      "start_ms": 47182,
      "duration_ms": 6552,
      "chords": [
        "Eb:min",
        "Db:maj",
        "Eb:min",
        "F:5",
        "F:5",
        "F:5"
      ],
      "sectionType": "Bridge",
      "sectionLetter": "D",
      "sectionFunction": "Development",
      "sectionLabel": "D",
      "tags": [
        "salami_annotated",
        "timing_confidence:high"
      ]
    },
    {
      "id": "transition_1",
      "start_ms": 53735,
      "duration_ms": 13094,
      "chords": [
        "F:5",
        "F:maj",
        "Bb:maj/5",
        "F:maj",
        "Bb:maj/5",
        "F:maj",
        "Eb:maj",
        "Bb:maj",
        "Bb:maj",
        "Eb:maj",
        "Bb:maj",
        "F:maj",
        "Bb:maj/5",
        "F:maj",
        "Bb:maj/5",
        "F:maj",
        "Eb:maj",
        "Bb:maj",
        "Bb:maj",
        "Eb:maj",
        "Bb:maj",
        "Bb:maj"
      ],
      "sectionType": "Transition",
      "sectionLetter": "E",
      "sectionFunction": "Transition",
      "sectionLabel": "E",
      "tags": [
        "salami_annotated",
        "timing_confidence:high"
      ]
    },
    {
      "id": "verse_2",
      "start_ms": 66829,
      "duration_ms": 13240,
      "chords": [
        "Bb:maj",
        "Eb:min",
        "Eb:min",
        "Eb:min",
        "Eb:min",
        "Eb:min",
        "Eb:min",
        "Eb:min",
        "Eb:min",
        "Eb:min"
      ],
      "sectionType": "Verse",
      "sectionLetter": "B",
      "sectionFunction": "MainTheme",
      "sectionLabel": "B",
      "tags": [
        "salami_annotated",
        "timing_confidence:high"
      ]
    },
    {
      "id": "chorus_2",
      "start_ms": 80069,
      "duration_ms": 26553,
      "chords": [
        "Eb:min",
        "F:5",
        "Bb:5",
        "F:5",
        "Eb:5",
        "F:5",
        "Bb:5",
        "F:5",
        "Gb:5",
        "G:5",
        "Ab:5",
        "Ab:5",
        "Eb:min",
        "Eb:min",
        "Eb:min",
        "Eb:min",
        "Eb:min",
        "F:5",
        "Bb:5",
        "F:5",
        "Eb:5",
        "F:5",
        "Bb:5",
        "F:5",
        "Gb:5",
        "G:5",
        "Ab:5",
        "Ab:5",
        "Eb:min",
        "Eb:min",
        "Eb:min",
        "Eb:min"
      ],
      "sectionType": "Chorus",
      "sectionLetter": "C",
      "sectionFunction": "Hook",
      "sectionLabel": "C",
      "tags": [
        "salami_annotated",
        "timing_confidence:high"
      ]
    },
    {
      "id": "bridge_2",
      "start_ms": 106623,
      "duration_ms": 6601,
      "chords": [
        "Db:maj",
        "Eb:min",
        "F:5",
        "F:5",
        "F:5"
      ],
      "sectionType": "Bridge",
      "sectionLetter": "D",
      "sectionFunction": "Development",
      "sectionLabel": "D",
      "tags": [
        "salami_annotated",
        "timing_confidence:high"
      ]
    },
    {
      "id": "transition_2",
      "start_ms": 113224,
      "duration_ms": 13170,
      "chords": [
        "F:5",
        "F:maj",
        "Bb:maj/5",
        "F:maj",
        "Bb:maj/5",
        "F:maj",
        "Eb:maj",
        "Bb:maj",
        "Bb:maj",
        "Eb:maj",
        "Bb:maj",
        "F:maj",
        "Bb:maj/5",
        "F:maj",
        "Bb:maj/5",
        "F:maj",
        "Eb:maj",
        "Bb:maj",
        "Bb:maj",
        "Eb:maj",
        "Bb:maj",
        "Bb:maj"
      ],
      "sectionType": "Transition",
      "sectionLetter": "E",
      "sectionFunction": "Transition",
      "sectionLabel": "E",
      "tags": [
        "salami_annotated",
        "timing_confidence:high"
      ]
    },
    {
      "id": "intro_2",
      "start_ms": 126394,
      "duration_ms": 19726,
      "chords": [
        "F:1/1",
        "Gb:1/1",
        "G:1/1",
        "Ab:1/1",
        "A:1/1",
        "Bb:1/1",
        "B:1/1",
        "C:1/1",
        "F:maj",
        "F#:maj",
        "G:maj",
        "G#:maj",
        "A:maj",
        "A#:maj",
        "B:maj",
        "C:maj",
        "F:maj",
        "F#:maj",
        "G:maj",
        "G#:maj",
        "A:maj",
        "A#:maj",
        "B:maj",
        "C:maj"
      ],
      "sectionType": "Intro",
      "sectionLetter": "A",
      "sectionFunction": "Introduction",
      "sectionLabel": "A",
      "tags": [
        "salami_annotated",
        "timing_confidence:high"
      ]
    },
    {
      "id": "prechorus_1",
      "start_ms": 146120,
      "duration_ms": 26858,
      "chords": [
        "F:maj",
        "Bb:maj",
        "F:maj",
        "Bb:maj",
        "F:maj",
        "Bb:maj",
        "F:maj",
        "Gb:5",
        "G:5",
        "Ab:maj",
        "Db:maj",
        "Ab:maj",
        "Db:maj",
        "Ab:maj",
        "Db:maj",
        "Ab:5",
        "A:5",
        "Bb:5",
        "B:5",
        "C:maj",
        "F:maj",
        "C:maj",
        "F:maj",
        "C:maj",
        "F:maj",
        "C:maj",
        "Db:5",
        "D:5",
        "Eb:maj",
        "Ab:maj",
        "Eb:maj",
        "Ab:maj",
        "Eb:maj",
        "Ab:maj",
        "Eb:maj",
        "Ab:maj",
        "Ab:maj"
      ],
      "sectionType": "PreChorus",
      "sectionLetter": "F",
      "sectionFunction": "Build",
      "sectionLabel": "F",
      "tags": [
        "salami_annotated",
        "timing_confidence:high"
      ]
    },
    {
      "id": "transition_3",
      "start_ms": 172978,
      "duration_ms": 13207,
      "chords": [
        "Ab:maj",
        "F:maj",
        "Bb:maj/5",
        "F:maj",
        "Bb:maj/5",
        "F:maj",
        "Eb:maj",
        "Bb:maj",
        "Bb:maj",
        "Eb:maj",
        "Bb:maj",
        "F:maj",
        "Bb:maj/5",
        "F:maj",
        "Bb:maj/5",
        "F:maj",
        "Eb:maj",
        "Bb:maj",
        "Bb:maj",
        "Eb:maj",
        "Bb:maj"
      ],
      "sectionType": "Transition",
      "sectionLetter": "E",
      "sectionFunction": "Transition",
      "sectionLabel": "E",
      "tags": [
        "salami_annotated",
        "timing_confidence:high"
      ]
    },
    {
      "id": "transition_4",
      "start_ms": 186186,
      "duration_ms": 13239,
      "chords": [
        "Bb:maj",
        "F:maj",
        "Bb:maj/5",
        "F:maj",
        "Bb:maj/5",
        "F:maj",
        "Eb:maj",
        "Bb:maj",
        "Bb:maj",
        "Eb:maj",
        "Bb:maj",
        "F:maj",
        "Bb:maj/5",
        "F:maj",
        "Bb:maj/5",
        "F:maj",
        "Eb:maj",
        "Bb:maj",
        "Bb:maj",
        "Eb:maj",
        "Bb:maj",
        "Bb:maj"
      ],
      "sectionType": "Transition",
      "sectionLetter": "E",
      "sectionFunction": "Transition",
      "sectionLabel": "E",
      "tags": [
        "salami_annotated",
        "timing_confidence:high"
      ]
    },
    {
      "id": "outro_1",
      "start_ms": 199426,
      "duration_ms": 47849,
      "chords": [
        "Bb:maj",
        "Eb:min",
        "Eb:min",
        "Eb:min",
        "Eb:min",
        "Eb:min",
        "Eb:min",
        "Eb:min",
        "Ab:5",
        "Ab:5",
        "N",
        "N",
        "N",
        "N",
        "N",
        "Ab:7",
        "N",
        "Ab:5",
        "Ab:5",
        "N",
        "N",
        "N"
      ],
      "sectionType": "Outro",
      "sectionLetter": "B",
      "sectionFunction": "Conclusion",
      "sectionLabel": "B'",
      "tags": [
        "salami_annotated",
        "timing_confidence:high"
      ]
    }
  ]
}